MANIFEST.in
README.md
requirements.txt
setup.py
src/xfact_lm.egg-info/PKG-INFO
src/xfact_lm.egg-info/SOURCES.txt
src/xfact_lm.egg-info/dependency_links.txt
src/xfact_lm.egg-info/requires.txt
src/xfact_lm.egg-info/top_level.txt
src/xfact_lslms/__init__.py
src/xfact_lslms/log_helper.py
src/xfact_lslms/client/__init__.py
src/xfact_lslms/client/lslms_client.py
src/xfact_lslms/service/__init__.py
src/xfact_lslms/service/agent.py
src/xfact_lslms/service/amq_communications.py
src/xfact_lslms/service/models.py