Metadata-Version: 1.2
Name: xfact-lm
Version: 0.2.50
Summary: xfact language model
Home-page: UNKNOWN
Author: James Thorne
Author-email: james@jamesthorne.com
License: UNKNOWN
Platform: UNKNOWN
Requires-Python: >=3.8
